acidfs/__init__.py
acidfs-2.0.dist-info/METADATA
acidfs-2.0.dist-info/WHEEL
acidfs-2.0.dist-info/top_level.txt
acidfs-2.0.dist-info/RECORD
