Metadata-Version: 2.1
Name: acidfs
Version: 2.0
Summary: ACID semantics for the filesystem.
Home-page: http://pylonsproject.org
Author: Chris Rossi
Author-email: pylons-discuss@googlegroups.com
License: BSD-derived (http://www.repoze.org/LICENSE.txt)
Keywords: git acid filesystem transaction
Platform: UNKNOWN
Classifier: Development Status :: 5 - Production/Stable
Classifier: Intended Audience :: Developers
Classifier: Topic :: Database
Classifier: License :: Repoze Public License
Requires-Dist: transaction
Provides-Extra: docs
Requires-Dist: Sphinx ; extra == 'docs'
Requires-Dist: pylons-sphinx-themes ; extra == 'docs'
Provides-Extra: testing
Requires-Dist: pytest ; extra == 'testing'
Requires-Dist: pytest-cov ; extra == 'testing'
Requires-Dist: nox ; extra == 'testing'
